CHANGES.rst
MANIFEST.in
README.rst
pytest_dbus_notification.py
setup.py
pytest_dbus_notification.egg-info/PKG-INFO
pytest_dbus_notification.egg-info/SOURCES.txt
pytest_dbus_notification.egg-info/dependency_links.txt
pytest_dbus_notification.egg-info/entry_points.txt
pytest_dbus_notification.egg-info/requires.txt
pytest_dbus_notification.egg-info/top_level.txt