Metadata-Version: 1.1
Name: pytest-dbus-notification
Version: 1.0.1
Summary: D-BUS notifications for pytest results.
Home-page: https://github.com/bmathieu33/pytest-dbus-notification
Author: Bertrand Mathieu
Author-email: bert.mathieu at gmail.com
License: UNKNOWN
Keywords: pytest,pytest-,dbus,py.test
Platform: UNKNOWN
Classifier: Development Status :: 5 - Production/Stable
Classifier: Intended Audience :: Developers
Classifier: License :: OSI Approved :: MIT License
Classifier: Operating System :: POSIX
Classifier: Programming Language :: Python
Classifier: Topic :: Desktop Environment
Classifier: Topic :: Software Development :: Testing
Classifier: Topic :: Utilities
